Workbook

Sheet интро
C3: Исследование выполнил: Линник Сергей
C4: Данные сгенерированы ChatGPT и не являются NDA
C6: Задачи исследования | D6: № | E6: Декомпозиция | F6: Выводы исследования
C7: Анализ продаж продуктовых сетей | D7: 1 | E7: Динамика продаж по магазинам | F7: Динамика продаж по магазинам зависит от ассортимента магазина и времени года. По всем магазинам наибольшее снижение продаж приходится на октябрь, максимальные приходятся на март и август. По магазину Бристоль максимальные продажи приходятся на июль, минимальные на октябрь. По магазину Мираторг максимальные продажи приходятся на март и май, минимальные на январь и ноябрь.
D8: 2 | E8: Анализ цен внутри товарной категории по магазинам | F8: Наиболее привлекательным магазином для клиентов является Пятерочка, наименее привлекательным - Лента
D9: 3 | E9: Суммарные продажи по магазинам | F9: Крупнейшим магазином по показателю GMV является О`Кей, наименьшим Билла.
C10: Сравнение поставщиков по объемам закупок | D10: 4 | E10: Анализ цен внутри категории по поставщикам
D11: 5 | E11: Суммарные продажи по поставщикам | F11: Крупнейшим поставщиком является Паста Зара, наимеьшим - Микоян
C12: Изучение продаж по категориям товаров | D12: 6 | E12: Суммарные продажи по категориям | F12: Наиболее доходная категория макароны, наименее доходная колбаса
D13: 7 | E13: Среднее количество по категориям (что покупают чаще) | F13: Наибольшее значение количества единиц в чеке приходится на молоко, наименьшее на сыр
C14: Изучение клиентов по географии и лайфтайму | D14: 8 | E14: Аналитика географии клиентов | F14: Наибольшее количество клиентов приходится на Россия, наименьшее на Беларусь
D15: 9 | E15: Кол-во дней с момента регистрациидо покупки | F15: Наибольшее часто встречающееся значение количества дней с момента регистрации приходится на диапазон 442-504 дня
D16: 10 | E16: Лайфтайм клиента | F16: Наиболее часто встречающееся значение количества месяцев, которое люди являются клиентами сотавляет 42--44 месяца
D17: 11 | E17: Частотность имен для рекламной компании | F17: Чаще всего стречаются имена Алевтина, Феврония, Василиса
D18: 12 | E18: Платежеспособность по странам | F18: Наиболее платежеспособное население приходится на Россию, наименее платежеспособное на Беларусь
C20: Отработка Hard Skills
C21: Преобразование типов и визуальное форматирование
C22: Условное форматирование данных
C23: Умные таблицы и работа с абсолютными и относительными ссылками
C24: Математические и текстовые функции
C25: Функции для работы с датой и временем
C26: Функции поиска и извлечения данных
C27: Сводные таблицы и срезы данных
C28: Построение диаграмм

Sheet Дашборд

Sheet Частотность имен
A3: Названия строк | B3: Количество по полю Имя
A4: Алевтина | B4: 6
A5: Феврония | B5: 6
A6: Василиса | B6: 6
A7: Любовь | B7: 5
A8: Эмилия | B8: 5
A9: Юлия | B9: 5
A10: Марфа | B10: 5
A11: Вера | B11: 5
A12: Жанна | B12: 5
A13: Лора | B13: 4
A14: Татьяна | B14: 4
A15: Любомир | B15: 4
... A240: Общий итог | B240: 434

Sheet Имена для рекламы
A1: ФИО | B1: Имя
A2: Сила Денисович Гурьев | B2: =IF(OR(RIGHT(MID(A2,SEARCH(" ",A2,SEARCH(" ",A2)+1)+1,99),3)="вич",RIGHT(MID(A2,SEARCH(" ",A2,SEARCH(" ",A2)+1)+1,99),3)="вна",RIGHT(MID(A2,SEARCH(" ",A2,SEARCH(" ",A2)+1)+1,99),2)="ич",RIGHT(MID(A2,SEARCH(" ",A2,SEARCH(" ",A2)+1)+1,99),4)="ична"), MID(A2,SEARCH(" ",A2)+1,SEARCH(" ",A2,SEARCH(" ",A2)+1)-SEARCH(" ",A2)-1), MID(A2,1,SEARCH(" ",A2)-1)) -> Сила
A3: Лора Болеславовна Потапова | B3: =IF(OR(RIGHT(MID(A3,SEARCH(" ",A3,SEARCH(" ",A3)+1)+1,99),3)="вич",RIGHT(MID(A3,SEARCH(" ",A3,SEARCH(" ",A3)+1)+1,99),3)="вна",RIGHT(MID(A3,SEARCH(" ",A3,SEARCH(" ",A3)+1)+1,99),2)="ич",RIGHT(MID(A3,SEARCH(" ",A3,SEARCH(" ",A3)+1)+1,99),4)="ична"), MID(A3,SEARCH(" ",A3)+1,SEARCH(" ",A3,SEARCH(" ",A3)+1)-SEARCH(" ",A3)-1), MID(A3,1,SEARCH(" ",A3)-1)) -> Лора
A4: Зоя Егоровна Третьякова | B4: =IF(OR(RIGHT(MID(A4,SEARCH(" ",A4,SEARCH(" ",A4)+1)+1,99),3)="вич",RIGHT(MID(A4,SEARCH(" ",A4,SEARCH(" ",A4)+1)+1,99),3)="вна",RIGHT(MID(A4,SEARCH(" ",A4,SEARCH(" ",A4)+1)+1,99),2)="ич",RIGHT(MID(A4,SEARCH(" ",A4,SEARCH(" ",A4)+1)+1,99),4)="ична"), MID(A4,SEARCH(" ",A4)+1,SEARCH(" ",A4,SEARCH(" ",A4)+1)-SEARCH(" ",A4)-1), MID(A4,1,SEARCH(" ",A4)-1)) -> Зоя
A5: Лапин Эрнест Антипович | B5: =IF(OR(RIGHT(MID(A5,SEARCH(" ",A5,SEARCH(" ",A5)+1)+1,99),3)="вич",RIGHT(MID(A5,SEARCH(" ",A5,SEARCH(" ",A5)+1)+1,99),3)="вна",RIGHT(MID(A5,SEARCH(" ",A5,SEARCH(" ",A5)+1)+1,99),2)="ич",RIGHT(MID(A5,SEARCH(" ",A5,SEARCH(" ",A5)+1)+1,99),4)="ична"), MID(A5,SEARCH(" ",A5)+1,SEARCH(" ",A5,SEARCH(" ",A5)+1)-SEARCH(" ",A5)-1), MID(A5,1,SEARCH(" ",A5)-1)) -> Эрнест
A6: Миронов Аверкий Зиновьевич | B6: =IF(OR(RIGHT(MID(A6,SEARCH(" ",A6,SEARCH(" ",A6)+1)+1,99),3)="вич",RIGHT(MID(A6,SEARCH(" ",A6,SEARCH(" ",A6)+1)+1,99),3)="вна",RIGHT(MID(A6,SEARCH(" ",A6,SEARCH(" ",A6)+1)+1,99),2)="ич",RIGHT(MID(A6,SEARCH(" ",A6,SEARCH(" ",A6)+1)+1,99),4)="ична"), MID(A6,SEARCH(" ",A6)+1,SEARCH(" ",A6,SEARCH(" ",A6)+1)-SEARCH(" ",A6)-1), MID(A6,1,SEARCH(" ",A6)-1)) -> Аверкий
A7: Анжелика Валериевна Рожкова | B7: =IF(OR(RIGHT(MID(A7,SEARCH(" ",A7,SEARCH(" ",A7)+1)+1,99),3)="вич",RIGHT(MID(A7,SEARCH(" ",A7,SEARCH(" ",A7)+1)+1,99),3)="вна",RIGHT(MID(A7,SEARCH(" ",A7,SEARCH(" ",A7)+1)+1,99),2)="ич",RIGHT(MID(A7,SEARCH(" ",A7,SEARCH(" ",A7)+1)+1,99),4)="ична"), MID(A7,SEARCH(" ",A7)+1,SEARCH(" ",A7,SEARCH(" ",A7)+1)-SEARCH(" ",A7)-1), MID(A7,1,SEARCH(" ",A7)-1)) -> Анжелика
A8: Никита Венедиктович Третьяков | B8: =IF(OR(RIGHT(MID(A8,SEARCH(" ",A8,SEARCH(" ",A8)+1)+1,99),3)="вич",RIGHT(MID(A8,SEARCH(" ",A8,SEARCH(" ",A8)+1)+1,99),3)="вна",RIGHT(MID(A8,SEARCH(" ",A8,SEARCH(" ",A8)+1)+1,99),2)="ич",RIGHT(MID(A8,SEARCH(" ",A8,SEARCH(" ",A8)+1)+1,99),4)="ична"), MID(A8,SEARCH(" ",A8)+1,SEARCH(" ",A8,SEARCH(" ",A8)+1)-SEARCH(" ",A8)-1), MID(A8,1,SEARCH(" ",A8)-1)) -> Никита
A9: Тимофеев Аполлинарий Фомич | B9: =IF(OR(RIGHT(MID(A9,SEARCH(" ",A9,SEARCH(" ",A9)+1)+1,99),3)="вич",RIGHT(MID(A9,SEARCH(" ",A9,SEARCH(" ",A9)+1)+1,99),3)="вна",RIGHT(MID(A9,SEARCH(" ",A9,SEARCH(" ",A9)+1)+1,99),2)="ич",RIGHT(MID(A9,SEARCH(" ",A9,SEARCH(" ",A9)+1)+1,99),4)="ична"), MID(A9,SEARCH(" ",A9)+1,SEARCH(" ",A9,SEARCH(" ",A9)+1)-SEARCH(" ",A9)-1), MID(A9,1,SEARCH(" ",A9)-1)) -> Аполлинарий
A10: Исакова Людмила Олеговна | B10: =IF(OR(RIGHT(MID(A10,SEARCH(" ",A10,SEARCH(" ",A10)+1)+1,99),3)="вич",RIGHT(MID(A10,SEARCH(" ",A10,SEARCH(" ",A10)+1)+1,99),3)="вна",RIGHT(MID(A10,SEARCH(" ",A10,SEARCH(" ",A10)+1)+1,99),2)="ич",RIGHT(MID(A10,SEARCH(" ",A10,SEARCH(" ",A10)+1)+1,99),4)="ична"), MID(A10,SEARCH(" ",A10)+1,SEARCH(" ",A10,SEARCH(" ",A10)+1)-SEARCH(" ",A10)-1), MID(A10,1,SEARCH(" ",A10)-1)) -> Людмила
A11: Демид Антонович Мясников | B11: =IF(OR(RIGHT(MID(A11,SEARCH(" ",A11,SEARCH(" ",A11)+1)+1,99),3)="вич",RIGHT(MID(A11,SEARCH(" ",A11,SEARCH(" ",A11)+1)+1,99),3)="вна",RIGHT(MID(A11,SEARCH(" ",A11,SEARCH(" ",A11)+1)+1,99),2)="ич",RIGHT(MID(A11,SEARCH(" ",A11,SEARCH(" ",A11)+1)+1,99),4)="ична"), MID(A11,SEARCH(" ",A11)+1,SEARCH(" ",A11,SEARCH(" ",A11)+1)-SEARCH(" ",A11)-1), MID(A11,1,SEARCH(" ",A11)-1)) -> Демид
A12: Антонина Борисовна Жданова | B12: =IF(OR(RIGHT(MID(A12,SEARCH(" ",A12,SEARCH(" ",A12)+1)+1,99),3)="вич",RIGHT(MID(A12,SEARCH(" ",A12,SEARCH(" ",A12)+1)+1,99),3)="вна",RIGHT(MID(A12,SEARCH(" ",A12,SEARCH(" ",A12)+1)+1,99),2)="ич",RIGHT(MID(A12,SEARCH(" ",A12,SEARCH(" ",A12)+1)+1,99),4)="ична"), MID(A12,SEARCH(" ",A12)+1,SEARCH(" ",A12,SEARCH(" ",A12)+1)-SEARCH(" ",A12)-1), MID(A12,1,SEARCH(" ",A12)-1)) -> Антонина
A13: Елизар Харлампьевич Мамонтов | B13: =IF(OR(RIGHT(MID(A13,SEARCH(" ",A13,SEARCH(" ",A13)+1)+1,99),3)="вич",RIGHT(MID(A13,SEARCH(" ",A13,SEARCH(" ",A13)+1)+1,99),3)="вна",RIGHT(MID(A13,SEARCH(" ",A13,SEARCH(" ",A13)+1)+1,99),2)="ич",RIGHT(MID(A13,SEARCH(" ",A13,SEARCH(" ",A13)+1)+1,99),4)="ична"), MID(A13,SEARCH(" ",A13)+1,SEARCH(" ",A13,SEARCH(" ",A13)+1)-SEARCH(" ",A13)-1), MID(A13,1,SEARCH(" ",A13)-1)) -> Елизар
... A435: Князев Платон Андреевич | B435: =IF(OR(RIGHT(MID(A435,SEARCH(" ",A435,SEARCH(" ",A435)+1)+1,99),3)="вич",RIGHT(MID(A435,SEARCH(" ",A435,SEARCH(" ",A435)+1)+1,99),3)="вна",RIGHT(MID(A435,SEARCH(" ",A435,SEARCH(" ",A435)+1)+1,99),2)="ич",RIGHT(MID(A435,SEARCH(" ",A435,SEARCH(" ",A435)+1)+1,99),4)="ична"), MID(A435,SEARCH(" ",A435)+1,SEARCH(" ",A435,SEARCH(" ",A435)+1)-SEARCH(" ",A435)-1), MID(A435,1,SEARCH(" ",A435)-1)) -> Платон

Sheet клиенты
A1: id клиента | B1: номер телефона клиента | C1: ФИО | D1: Программа лояльности клиента | E1: Дата регистрации клиента | F1: Коды стран | G1: Страна клиента | H1: Текущая дата | I1: Дни | J1: Лайфтайм (мес) | K1: Имя
A2: 194 | B2: +7 273-904-5457 | C2: Сила Денисович Гурьев | D2: да | E2: 44924 | F2: +7 | G2: =INDEX('коды стран'!$A$2:$A$6, MATCH(F2, 'коды стран'!$B$2:$B$6, 0)) -> Россия | H2: =TODAY() -> 46076 | I2: =Таблица3[[#This Row],[Текущая дата]]-Продажи[[#This Row],[Дата регистрации клиента]] -> 1329 | J2: =ROUND((Таблица3[[#This Row],[Текущая дата]] - Продажи[[#This Row],[Дата регистрации клиента]]) / 30, 0) -> 44
A3: 267 | B3: +7 632-222-4524 | C3: Лора Болеславовна Потапова | D3: да | E3: 44910 | F3: +7 | G3: =INDEX('коды стран'!$A$2:$A$6, MATCH(F3, 'коды стран'!$B$2:$B$6, 0)) -> Россия | H3: =TODAY() -> 46076 | I3: =Таблица3[[#This Row],[Текущая дата]]-Продажи[[#This Row],[Дата регистрации клиента]] -> 1326 | J3: =ROUND((Таблица3[[#This Row],[Текущая дата]] - Продажи[[#This Row],[Дата регистрации клиента]]) / 30, 0) -> 44 | K3: =LEFT(C3,#REF!- 1) -> #REF!
A4: 458 | B4: +7 089-779-0837 | C4: Зоя Егоровна Третьякова | D4: да | E4: 44694 | F4: +7 | G4: =INDEX('коды стран'!$A$2:$A$6, MATCH(F4, 'коды стран'!$B$2:$B$6, 0)) -> Россия | H4: =TODAY() -> 46076 | I4: =Таблица3[[#This Row],[Текущая дата]]-Продажи[[#This Row],[Дата регистрации клиента]] -> 1234 | J4: =ROUND((Таблица3[[#This Row],[Текущая дата]] - Продажи[[#This Row],[Дата регистрации клиента]]) / 30, 0) -> 41 | K4: =LEFT(C4,#REF!- 1) -> #REF!
A5: 73 | B5: +380 487-238-5930 | C5: Лапин Эрнест Антипович | D5: да | E5: 44665 | F5: +380 | G5: =INDEX('коды стран'!$A$2:$A$6, MATCH(F5, 'коды стран'!$B$2:$B$6, 0)) -> Украина | H5: =TODAY() -> 46076 | I5: =Таблица3[[#This Row],[Текущая дата]]-Продажи[[#This Row],[Дата регистрации клиента]] -> 1433 | J5: =ROUND((Таблица3[[#This Row],[Текущая дата]] - Продажи[[#This Row],[Дата регистрации клиента]]) / 30, 0) -> 48 | K5: =LEFT(C5,#REF!- 1) -> #REF!
A6: 436 | B6: +7 613-538-5501 | C6: Миронов Аверкий Зиновьевич | D6: нет | E6: 44683 | F6: +7 | G6: =INDEX('коды стран'!$A$2:$A$6, MATCH(F6, 'коды стран'!$B$2:$B$6, 0)) -> Россия | H6: =TODAY() -> 46076 | I6: =Таблица3[[#This Row],[Текущая дата]]-Продажи[[#This Row],[Дата регистрации клиента]] -> 1499 | J6: =ROUND((Таблица3[[#This Row],[Текущая дата]] - Продажи[[#This Row],[Дата регистрации клиента]]) / 30, 0) -> 50 | K6: =LEFT(C6,#REF!- 1) -> #REF!
A7: 448 | B7: +7 984-361-4421 | C7: Анжелика Валериевна Рожкова | D7: нет | E7: 44770 | F7: +7 | G7: =INDEX('коды стран'!$A$2:$A$6, MATCH(F7, 'коды стран'!$B$2:$B$6, 0)) -> Россия | H7: =TODAY() -> 46076 | I7: =Таблица3[[#This Row],[Текущая дата]]-Продажи[[#This Row],[Дата регистрации клиента]] -> 1494 | J7: =ROUND((Таблица3[[#This Row],[Текущая дата]] - Продажи[[#This Row],[Дата регистрации клиента]]) / 30, 0) -> 50 | K7: =LEFT(C7,#REF!- 1) -> #REF!
A8: 21 | B8: +375 299-252-6550 | C8: Никита Венедиктович Третьяков | D8: да | E8: 44881 | F8: +375 | G8: =INDEX('коды стран'!$A$2:$A$6, MATCH(F8, 'коды стран'!$B$2:$B$6, 0)) -> Беларусь | H8: =TODAY() -> 46076 | I8: =Таблица3[[#This Row],[Текущая дата]]-Продажи[[#This Row],[Дата регистрации клиента]] -> 1338 | J8: =ROUND((Таблица3[[#This Row],[Текущая дата]] - Продажи[[#This Row],[Дата регистрации клиента]]) / 30, 0) -> 45 | K8: =LEFT(C8,#REF!- 1) -> #REF!
A9: 292 | B9: +7 421-153-6302 | C9: Тимофеев Аполлинарий Фомич | D9: нет | E9: 44608 | F9: +7 | G9: =INDEX('коды стран'!$A$2:$A$6, MATCH(F9, 'коды стран'!$B$2:$B$6, 0)) -> Россия | H9: =TODAY() -> 46076 | I9: =Таблица3[[#This Row],[Текущая дата]]-Продажи[[#This Row],[Дата регистрации клиента]] -> 1457 | J9: =ROUND((Таблица3[[#This Row],[Текущая дата]] - Продажи[[#This Row],[Дата регистрации клиента]]) / 30, 0) -> 49 | K9: =LEFT(C9,#REF!- 1) -> #REF!
A10: 296 | B10: +998 997-462-0828 | C10: Исакова Людмила Олеговна | D10: нет | E10: 44758 | F10: +998 | G10: =INDEX('коды стран'!$A$2:$A$6, MATCH(F10, 'коды стран'!$B$2:$B$6, 0)) -> Узбекистан | H10: =TODAY() -> 46076 | I10: =Таблица3[[#This Row],[Текущая дата]]-Продажи[[#This Row],[Дата регистрации клиента]] -> 1392 | J10: =ROUND((Таблица3[[#This Row],[Текущая дата]] - Продажи[[#This Row],[Дата регистрации клиента]]) / 30, 0) -> 46 | K10: =LEFT(C10,#REF!- 1) -> #REF!
A11: 221 | B11: +992 520-869-0598 | C11: Демид Антонович Мясников | D11: да | E11: 44820 | F11: +992 | G11: =INDEX('коды стран'!$A$2:$A$6, MATCH(F11, 'коды стран'!$B$2:$B$6, 0)) -> Таджикистан | H11: =TODAY() -> 46076 | I11: =Таблица3[[#This Row],[Текущая дата]]-Продажи[[#This Row],[Дата регистрации клиента]] -> 1377 | J11: =ROUND((Таблица3[[#This Row],[Текущая дата]] - Продажи[[#This Row],[Дата регистрации клиента]]) / 30, 0) -> 46 | K11: =LEFT(C11,#REF!- 1) -> #REF!
A12: 53 | B12: +7 189-378-6167 | C12: Антонина Борисовна Жданова | D12: нет | E12: 44593 | F12: +7 | G12: =INDEX('коды стран'!$A$2:$A$6, MATCH(F12, 'коды стран'!$B$2:$B$6, 0)) -> Россия | H12: =TODAY() -> 46076 | I12: =Таблица3[[#This Row],[Текущая дата]]-Продажи[[#This Row],[Дата регистрации клиента]] -> 1422 | J12: =ROUND((Таблица3[[#This Row],[Текущая дата]] - Продажи[[#This Row],[Дата регистрации клиента]]) / 30, 0) -> 47 | K12: =LEFT(C12,#REF!- 1) -> #REF!
A13: 45 | B13: +998 714-433-6940 | C13: Елизар Харлампьевич Мамонтов | D13: да | E13: 44662 | F13: +998 | G13: =INDEX('коды стран'!$A$2:$A$6, MATCH(F13, 'коды стран'!$B$2:$B$6, 0)) -> Узбекистан | H13: =TODAY() -> 46076 | I13: =Таблица3[[#This Row],[Текущая дата]]-Продажи[[#This Row],[Дата регистрации клиента]] -> 1420 | J13: =ROUND((Таблица3[[#This Row],[Текущая дата]] - Продажи[[#This Row],[Дата регистрации клиента]]) / 30, 0) -> 47 | K13: =LEFT(C13,#REF!- 1) -> #REF!
A14: 196 | B14: +7 352-977-7374 | C14: Петрова Майя Богдановна | D14: да | E14: 44835 | F14: +7 | G14: =INDEX('коды стран'!$A$2:$A$6, MATCH(F14, 'коды стран'!$B$2:$B$6, 0)) -> Россия | H14: =TODAY() -> 46076 | I14: =Таблица3[[#This Row],[Текущая дата]]-Продажи[[#This Row],[Дата регистрации клиента]] -> 1218 | J14: =ROUND((Таблица3[[#This Row],[Текущая дата]] - Продажи[[#This Row],[Дата регистрации клиента]]) / 30, 0) -> 41 | K14: =LEFT(C14,#REF!- 1) -> #REF!
... A435: 394 | B435: +7 450-475-2540 | C435: Князев Платон Андреевич | D435: да | E435: 44708 | F435: +7 | G435: =INDEX('коды стран'!$A$2:$A$6, MATCH(F435, 'коды стран'!$B$2:$B$6, 0)) -> Россия | H435: =TODAY() -> 46076 | I435: =Таблица3[[#This Row],[Текущая дата]]-Продажи[[#This Row],[Дата регистрации клиента]] -> 1200 | J435: =ROUND((Таблица3[[#This Row],[Текущая дата]] - Продажи[[#This Row],[Дата регистрации клиента]]) / 30, 0) -> 40 | K435: =LEFT(C435,#REF!- 1) -> #REF!

Sheet Суммарные продажи по поставщика
A3: Поставщик | B3: Сумма по полю сумма чека
A4: Паста Зара | B4: 29430
A5: Фруктовый сад | B5: 24872
A6: Сырная долина | B6: 24200
A7: Greenfield | B7: 21191
A8: Бабаевский | B8: 20462
A9: Борилла | B9: 20345
A10: Домик в деревне | B10: 18739
A11: Pringles | B11: 18368
A12: Белый Злат | B12: 17471
A13: Рот Фронт | B13: 16874
A14: Jacobs | B14: 15751
A15: Овощной ряд | B15: 15581
... A82: Общий итог | B82: 800433

Sheet Среднее количесво по категориям
A3: Названия строк | B3: Среднее по полю кол-во штук в чеке
A4: Молоко | B4: 3.2380952
A5: Рис | B5: 3.1875
A6: Овощи | B6: 3.1463415
A7: Сахар | B7: 3.1355932
A8: Рыба | B8: 3.1282051
A9: Мясо | B9: 3.1272727
A10: Хлеб | B10: 3.0909091
A11: Соль | B11: 3.0754717
A12: Печенье | B12: 3.0638298
A13: Чипсы | B13: 3.0588235
A14: Кофе | B14: 3.047619
A15: Конфеты | B15: 2.983871
... A24: Общий итог | B24: 2.99

Sheet Суммарные продажи по категориям
A3: Названия строк | B3: Сумма по полю сумма чека
A4: Макароны | B4: 66945
A5: Конфеты | B5: 48797
A6: Мясо | B6: 47223
A7: Сок | B7: 45862
A8: Чипсы | B8: 44539
A9: Соль | B9: 44468
A10: Сыр | B10: 44265
A11: Сахар | B11: 44151
A12: Чай | B12: 43626
A13: Хлеб | B13: 42352
A14: Молоко | B14: 42165
A15: Йогурт | B15: 41745
... A24: Общий итог | B24: 800433

Sheet продажи
A1: id чека | B1: id товара | C1: цена за шт в рублях | D1: кол-во штук в чеке | E1: сумма чека | F1: дата создания чека | G1: магазин покупки | H1: id клиента | I1: Категория товара | J1: Средняя цена в категории за шт | K1: Выгода для клиента | L1: Поставщик товара | M1: Выгода для магазина | N1: Средняя стоимость в категории по поставщику | O1: Дата регистрации клиента | P1: количество дней с момента регистрации | Q1: Страны
A2: 1 | B2: 300 | C2: 103 | D2: 4 | E2: 412 | F2: 45187 | G2: Бристоль | H2: 315 | I2: =VLOOKUP(B2,товар!$A$1:$C$433,2,FALSE) -> Сахар | J2: =AVERAGEIF($I$2:$I$1001,I2,$C$2:$C$1001) -> 252.76271 | K2: =C2/J2-1 -> -0.59250319 | L2: =VLOOKUP(B2,товар!$A$1:$C$433,3,FALSE) -> Продимекс | M2: =C2/N2-1 -> -0.57172557 | N2: =AVERAGEIFS($C$2:$C$1001,$I$2:$I$1001,I2,$L$2:$L$1001,L2) -> 240.5 | O2: =VLOOKUP(H2,клиенты!$A$2:$G$435,5,FALSE) -> 44747 | P2: =Продажи[[#This Row],[дата создания чека]]-Продажи[[#This Row],[Дата регистрации клиента]] -> 440 | Q2: =VLOOKUP(H2,Таблица3[],7,FALSE) -> Узбекистан
A3: 2 | B3: 486 | C3: 296 | D3: 3 | E3: 888 | F3: 45083 | G3: Дикси | H3: 253 | I3: =VLOOKUP(B3,товар!$A$1:$C$433,2,FALSE) -> Соль | J3: =AVERAGEIF($I$2:$I$1001,I3,$C$2:$C$1001) -> 264.86792 | K3: =C3/J3-1 -> 0.11753811 | L3: =VLOOKUP(B3,товар!$A$1:$C$433,3,FALSE) -> Илецкая | M3: =C3/N3-1 -> 0.24282715 | N3: =AVERAGEIFS($C$2:$C$1001,$I$2:$I$1001,I3,$L$2:$L$1001,L3) -> 238.16667 | O3: =VLOOKUP(H3,клиенты!$A$2:$G$435,5,FALSE) -> 44750 | P3: =Продажи[[#This Row],[дата создания чека]]-Продажи[[#This Row],[Дата регистрации клиента]] -> 333 | Q3: =VLOOKUP(H3,Таблица3[],7,FALSE) -> Беларусь
A4: 3 | B4: 76 | C4: 139 | D4: 5 | E4: 695 | F4: 45363 | G4: Городской Супермаркет | H4: 12 | I4: =VLOOKUP(B4,товар!$A$1:$C$433,2,FALSE) -> Печенье | J4: =AVERAGEIF($I$2:$I$1001,I4,$C$2:$C$1001) -> 283.46809 | K4: =C4/J4-1 -> -0.50964497 | L4: =VLOOKUP(B4,товар!$A$1:$C$433,3,FALSE) -> Юбилейное | M4: =C4/N4-1 -> -0.40200765 | N4: =AVERAGEIFS($C$2:$C$1001,$I$2:$I$1001,I4,$L$2:$L$1001,L4) -> 232.44444 | O4: =VLOOKUP(H4,клиенты!$A$2:$G$435,5,FALSE) -> 44842 | P4: =Продажи[[#This Row],[дата создания чека]]-Продажи[[#This Row],[Дата регистрации клиента]] -> 521 | Q4: =VLOOKUP(H4,Таблица3[],7,FALSE) -> Беларусь
A5: 4 | B5: 240 | C5: 141 | D5: 5 | E5: 705 | F5: 45262 | G5: Верный | H5: 116 | I5: =VLOOKUP(B5,товар!$A$1:$C$433,2,FALSE) -> Макароны | J5: =AVERAGEIF($I$2:$I$1001,I5,$C$2:$C$1001) -> 265.47674 | K5: =C5/J5-1 -> -0.46888003 | L5: =VLOOKUP(B5,товар!$A$1:$C$433,3,FALSE) -> Борилла | M5: =C5/N5-1 -> -0.40323993 | N5: =AVERAGEIFS($C$2:$C$1001,$I$2:$I$1001,I5,$L$2:$L$1001,L5) -> 236.27586 | O5: =VLOOKUP(H5,клиенты!$A$2:$G$435,5,FALSE) -> 44643 | P5: =Продажи[[#This Row],[дата создания чека]]-Продажи[[#This Row],[Дата регистрации клиента]] -> 619 | Q5: =VLOOKUP(H5,Таблица3[],7,FALSE) -> Россия
A6: 5 | B6: 32 | C6: 123 | D6: 2 | E6: 246 | F6: 45151 | G6: Спар | H6: 471 | I6: =VLOOKUP(B6,товар!$A$1:$C$433,2,FALSE) -> Овощи | J6: =AVERAGEIF($I$2:$I$1001,I6,$C$2:$C$1001) -> 250.4878 | K6: =C6/J6-1 -> -0.50895813 | L6: =VLOOKUP(B6,товар!$A$1:$C$433,3,FALSE) -> Зеленая грядка | M6: =C6/N6-1 -> -0.22738693 | N6: =AVERAGEIFS($C$2:$C$1001,$I$2:$I$1001,I6,$L$2:$L$1001,L6) -> 159.2 | O6: =VLOOKUP(H6,клиенты!$A$2:$G$435,5,FALSE) -> 44577 | P6: =Продажи[[#This Row],[дата создания чека]]-Продажи[[#This Row],[Дата регистрации клиента]] -> 574 | Q6: =VLOOKUP(H6,Таблица3[],7,FALSE) -> Украина
A7: 6 | B7: 162 | C7: 452 | D7: 2 | E7: 904 | F7: 45281 | G7: Бристоль | H7: 374 | I7: =VLOOKUP(B7,товар!$A$1:$C$433,2,FALSE) -> Сок | J7: =AVERAGEIF($I$2:$I$1001,I7,$C$2:$C$1001) -> 268.60345 | K7: =C7/J7-1 -> 0.6827781 | L7: =VLOOKUP(B7,товар!$A$1:$C$433,3,FALSE) -> Фруктовый сад | M7: =C7/N7-1 -> 0.60301452 | N7: =AVERAGEIFS($C$2:$C$1001,$I$2:$I$1001,I7,$L$2:$L$1001,L7) -> 281.96875 | O7: =VLOOKUP(H7,клиенты!$A$2:$G$435,5,FALSE) -> 44582 | P7: =Продажи[[#This Row],[дата создания чека]]-Продажи[[#This Row],[Дата регистрации клиента]] -> 699 | Q7: =VLOOKUP(H7,Таблица3[],7,FALSE) -> Украина
A8: 7 | B8: 323 | C8: 149 | D8: 5 | E8: 745 | F8: 45349 | G8: Карусель | H8: 477 | I8: =VLOOKUP(B8,товар!$A$1:$C$433,2,FALSE) -> Рыба | J8: =AVERAGEIF($I$2:$I$1001,I8,$C$2:$C$1001) -> 258.51282 | K8: =C8/J8-1 -> -0.42362626 | L8: =VLOOKUP(B8,товар!$A$1:$C$433,3,FALSE) -> Меридиан | M8: =C8/N8-1 -> -0.42834575 | N8: =AVERAGEIFS($C$2:$C$1001,$I$2:$I$1001,I8,$L$2:$L$1001,L8) -> 260.64706 | O8: =VLOOKUP(H8,клиенты!$A$2:$G$435,5,FALSE) -> 44738 | P8: =Продажи[[#This Row],[дата создания чека]]-Продажи[[#This Row],[Дата регистрации клиента]] -> 611 | Q8: =VLOOKUP(H8,Таблица3[],7,FALSE) -> Узбекистан
A9: 8 | B9: 60 | C9: 489 | D9: 4 | E9: 1956 | F9: 45327 | G9: Мираторг | H9: 335 | I9: =VLOOKUP(B9,товар!$A$1:$C$433,2,FALSE) -> Кофе | J9: =AVERAGEIF($I$2:$I$1001,I9,$C$2:$C$1001) -> 249.02381 | K9: =C9/J9-1 -> 0.96366765 | L9: =VLOOKUP(B9,товар!$A$1:$C$433,3,FALSE) -> Jacobs | M9: =C9/N9-1 -> 0.77038872 | N9: =AVERAGEIFS($C$2:$C$1001,$I$2:$I$1001,I9,$L$2:$L$1001,L9) -> 276.21053 | O9: =VLOOKUP(H9,клиенты!$A$2:$G$435,5,FALSE) -> 44619 | P9: =Продажи[[#This Row],[дата создания чека]]-Продажи[[#This Row],[Дата регистрации клиента]] -> 708 | Q9: =VLOOKUP(H9,Таблица3[],7,FALSE) -> Узбекистан
A10: 9 | B10: 401 | C10: 416 | D10: 5 | E10: 2080 | F10: 45376 | G10: Мосмарт | H10: 350 | I10: =VLOOKUP(B10,товар!$A$1:$C$433,2,FALSE) -> Чай | J10: =AVERAGEIF($I$2:$I$1001,I10,$C$2:$C$1001) -> 271.18182 | K10: =C10/J10-1 -> 0.53402615 | L10: =VLOOKUP(B10,товар!$A$1:$C$433,3,FALSE) -> Greenfield | M10: =C10/N10-1 -> 0.42732377 | N10: =AVERAGEIFS($C$2:$C$1001,$I$2:$I$1001,I10,$L$2:$L$1001,L10) -> 291.45455 | O10: =VLOOKUP(H10,клиенты!$A$2:$G$435,5,FALSE) -> 44684 | P10: =Продажи[[#This Row],[дата создания чека]]-Продажи[[#This Row],[Дата регистрации клиента]] -> 692 | Q10: =VLOOKUP(H10,Таблица3[],7,FALSE) -> Украина
A11: 10 | B11: 100 | C11: 449 | D11: 2 | E11: 898 | F11: 45032 | G11: Карусель | H11: 413 | I11: =VLOOKUP(B11,товар!$A$1:$C$433,2,FALSE) -> Йогурт | J11: =AVERAGEIF($I$2:$I$1001,I11,$C$2:$C$1001) -> 263.25424 | K11: =C11/J11-1 -> 0.70557559 | L11: =VLOOKUP(B11,товар!$A$1:$C$433,3,FALSE) -> Ростагроэкспорт | M11: =C11/N11-1 -> 0.7417777 | N11: =AVERAGEIFS($C$2:$C$1001,$I$2:$I$1001,I11,$L$2:$L$1001,L11) -> 257.78261 | O11: =VLOOKUP(H11,клиенты!$A$2:$G$435,5,FALSE) -> 44699 | P11: =Продажи[[#This Row],[дата создания чека]]-Продажи[[#This Row],[Дата регистрации клиента]] -> 333 | Q11: =VLOOKUP(H11,Таблица3[],7,FALSE) -> Россия
A12: 11 | B12: 217 | C12: 296 | D12: 2 | E12: 592 | F12: 45136 | G12: Карусель | H12: 495 | I12: =VLOOKUP(B12,товар!$A$1:$C$433,2,FALSE) -> Мясо | J12: =AVERAGEIF($I$2:$I$1001,I12,$C$2:$C$1001) -> 271.74545 | K12: =C12/J12-1 -> 0.08925465 | L12: =VLOOKUP(B12,товар!$A$1:$C$433,3,FALSE) -> Агрокомплекс | M12: =C12/N12-1 -> -0.048843188 | N12: =AVERAGEIFS($C$2:$C$1001,$I$2:$I$1001,I12,$L$2:$L$1001,L12) -> 311.2 | O12: =VLOOKUP(H12,клиенты!$A$2:$G$435,5,FALSE) -> 44654 | P12: =Продажи[[#This Row],[дата создания чека]]-Продажи[[#This Row],[Дата регистрации клиента]] -> 482 | Q12: =VLOOKUP(H12,Таблица3[],7,FALSE) -> Узбекистан
A13: 12 | B13: 445 | C13: 109 | D13: 5 | E13: 545 | F13: 45394 | G13: Мираторг | H13: 353 | I13: =VLOOKUP(B13,товар!$A$1:$C$433,2,FALSE) -> Сахар | J13: =AVERAGEIF($I$2:$I$1001,I13,$C$2:$C$1001) -> 252.76271 | K13: =C13/J13-1 -> -0.56876551 | L13: =VLOOKUP(B13,товар!$A$1:$C$433,3,FALSE) -> Сладов | M13: =C13/N13-1 -> -0.5463374 | N13: =AVERAGEIFS($C$2:$C$1001,$I$2:$I$1001,I13,$L$2:$L$1001,L13) -> 240.26667 | O13: =VLOOKUP(H13,клиенты!$A$2:$G$435,5,FALSE) -> 44656 | P13: =Продажи[[#This Row],[дата создания чека]]-Продажи[[#This Row],[Дата регистрации клиента]] -> 738 | Q13: =VLOOKUP(H13,Таблица3[],7,FALSE) -> Таджикистан
... A1001: 1000 | B1001: 296 | C1001: 453 | D1001: 1 | E1001: 453 | F1001: 45265 | G1001: Мосмарт | H1001: 167 | I1001: =VLOOKUP(B1001,товар!$A$1:$C$433,2,FALSE) -> Крупа | J1001: =AVERAGEIF($I$2:$I$1001,I1001,$C$2:$C$1001) -> 255.11628 | K1001: =C1001/J1001-1 -> 0.77566089 | L1001: =VLOOKUP(B1001,товар!$A$1:$C$433,3,FALSE) -> Мистраль | M1001: =C1001/N1001-1 -> 0.80977259 | N1001: =AVERAGEIFS($C$2:$C$1001,$I$2:$I$1001,I1001,$L$2:$L$1001,L1001) -> 250.30769 | O1001: =VLOOKUP(H1001,клиенты!$A$2:$G$435,5,FALSE) -> 44563 | P1001: =Продажи[[#This Row],[дата создания чека]]-Продажи[[#This Row],[Дата регистрации клиента]] -> 702 | Q1001: =VLOOKUP(H1001,Таблица3[],7,FALSE) -> Узбекистан

Sheet География клиентов
A3: Названия строк | B3: Количество по полю id клиента
A4: Россия | B4: 146
A5: Узбекистан | B5: 85
A6: Украина | B6: 78
A7: Таджикистан | B7: 74
A8: Беларусь | B8: 51
A9: Общий итог | B9: 434

Sheet Продажи товаров
A1: магазин покупки | B1: Мираторг
A3: Названия строк | B3: Сумма по полю сумма чека
A4: 2023 | B4: 27562
A5: янв | B5: 88
A6: фев | B6: 534
A7: мар | B7: 6221
A8: апр | B8: 1240
A9: май | B9: 5511
A10: июн | B10: 3074
A11: июл | B11: 1946
A12: авг | B12: 1310
A13: сен | B13: 934
A14: окт | B14: 4577
A15: ноя | B15: 183
... A22: Общий итог | B22: 40029

Sheet Выгода клиентам
A3: Названия строк | B3: Среднее по полю Выгода для клиента
A4: Лента | B4: 0.10062699
A5: Седьмой Континент | B5: 0.081840255
A6: Городской Супермаркет | B6: 0.05896841
A7: Билла | B7: 0.056287666
A8: Метро | B8: 0.047135773
A9: Азбука Вкуса | B9: 0.036131084
A10: Мосмарт | B10: 0.023330794
A11: Мираторг | B11: 0.010296277
A12: Карусель | B12: 0.0070069985
A13: Ароматный Мир | B13: 0.0052821685
A14: Бристоль | B14: -0.0080940543
A15: Дикси | B15: -0.009488577
... A23: Пятерочка | B23: -0.10170732

Sheet Суммарные продажи по магазинам
A3: Продуктовая сеть | B3: GMV
A4: О'кей | B4: 52844
A5: Гиперглобус | B5: 51789
A6: Мосмарт | B6: 49580
A7: Спар | B7: 48746
A8: Верный | B8: 47028
A9: Городской Супермаркет | B9: 43098
A10: Ароматный Мир | B10: 42837
A11: Седьмой Континент | B11: 41106
A12: Бристоль | B12: 41010
A13: Мираторг | B13: 40029
A14: Метро | B14: 39168
A15: Лента | B15: 38312
... A24: Общий итог | B24: 800433

Sheet Платежеспособность
A3: Названия строк | B3: Сумма по полю сумма чека
A4: Россия | B4: 251330
A5: Узбекистан | B5: 163294
A6: Украина | B6: 147543
A7: Таджикистан | B7: 139473
A8: Беларусь | B8: 98793

Sheet товар
A1: id товара | B1: категория товара | C1: поставщик
A2: 300 | B2: Сахар | C2: Продимекс
A3: 486 | B3: Соль | C3: Илецкая
A4: 76 | B4: Печенье | C4: Юбилейное
A5: 240 | B5: Макароны | C5: Борилла
A6: 32 | B6: Овощи | C6: Зеленая грядка
A7: 162 | B7: Сок | C7: Фруктовый сад
A8: 323 | B8: Рыба | C8: Меридиан
A9: 60 | B9: Кофе | C9: Jacobs
A10: 401 | B10: Чай | C10: Greenfield
A11: 100 | B11: Йогурт | C11: Ростагроэкспорт
A12: 217 | B12: Мясо | C12: Агрокомплекс
A13: 445 | B13: Сахар | C13: Сладов
... A433: 469 | B433: Сахар | C433: Сладов

Sheet коды стран
A1: Страна | B1: Код
A2: Беларусь | B2: +375
A3: Россия | B3: +7
A4: Таджикистан | B4: +992
A5: Узбекистан | B5: +998
A6: Украина | B6: +380
